setup.py
plumb_util/__init__.py
plumb_util/args.py
plumb_util/dns_srv.py
plumb_util/mongo.py
plumb_util.egg-info/PKG-INFO
plumb_util.egg-info/SOURCES.txt
plumb_util.egg-info/dependency_links.txt
plumb_util.egg-info/requires.txt
plumb_util.egg-info/top_level.txt