Metadata-Version: 1.0
Name: plumb-util
Version: 1.0
Summary: Plumbing utility library
Home-page: http://github.com/LuminosoInsight/plumb_util
Author: Luminoso Technologies, Inc.
Author-email: dev@luminoso.com
License: MIT
Platform: any
